fact/__init__.py
fact/generator/__init__.py
fact/generator/comprobante.xml
fact/generator/contants.py
fact/generator/generator33.py
fact/generator/generator40.py
fact/generator/generator_abstract.py
fact/generator/services.py
fact/generator/utils.py
fact/generator/cadenaoriginal_3_3_local/AcreditamientoIEPS10.xslt
fact/generator/cadenaoriginal_3_3_local/ComercioExterior10.xslt
fact/generator/cadenaoriginal_3_3_local/ComercioExterior11.xslt
fact/generator/cadenaoriginal_3_3_local/GastosHidrocarburos10.xslt
fact/generator/cadenaoriginal_3_3_local/IngresosHidrocarburos.xslt
fact/generator/cadenaoriginal_3_3_local/Pagos10.xslt
fact/generator/cadenaoriginal_3_3_local/TuristaPasajeroExtranjero.xslt
fact/generator/cadenaoriginal_3_3_local/__init__.py
fact/generator/cadenaoriginal_3_3_local/aerolineas.xslt
fact/generator/cadenaoriginal_3_3_local/cadena_original_carta_porte20.xslt
fact/generator/cadenaoriginal_3_3_local/cadena_original_cartaporte.xslt
fact/generator/cadenaoriginal_3_3_local/cadenaoriginal_3_3.xslt
fact/generator/cadenaoriginal_3_3_local/cadenaoriginal_4_0.xslt
fact/generator/cadenaoriginal_3_3_local/certificadodedestruccion.xslt
fact/generator/cadenaoriginal_3_3_local/cfdiregistrofiscal.xslt
fact/generator/cadenaoriginal_3_3_local/consumodeCombustibles11.xslt
fact/generator/cadenaoriginal_3_3_local/consumodecombustibles.xslt
fact/generator/cadenaoriginal_3_3_local/detallista.xslt
fact/generator/cadenaoriginal_3_3_local/divisas.xslt
fact/generator/cadenaoriginal_3_3_local/donat11.xslt
fact/generator/cadenaoriginal_3_3_local/ecb.xslt
fact/generator/cadenaoriginal_3_3_local/ecc.xslt
fact/generator/cadenaoriginal_3_3_local/ecc11.xslt
fact/generator/cadenaoriginal_3_3_local/ecc12.xslt
fact/generator/cadenaoriginal_3_3_local/iedu.xslt
fact/generator/cadenaoriginal_3_3_local/implocal.xslt
fact/generator/cadenaoriginal_3_3_local/ine11.xslt
fact/generator/cadenaoriginal_3_3_local/leyendasFisc.xslt
fact/generator/cadenaoriginal_3_3_local/nomina11.xslt
agv_fact-1.0.3.11.dist-info/LICENSE
agv_fact-1.0.3.11.dist-info/METADATA
agv_fact-1.0.3.11.dist-info/WHEEL
agv_fact-1.0.3.11.dist-info/top_level.txt
agv_fact-1.0.3.11.dist-info/RECORD
