Metadata-Version: 2.1
Name: agv-fact
Version: 1.0.3.11
Summary: Libreria para generar xml y realizar el timbrado
Home-page: https://github.com/pypa/fact
Author: Andres Alvarado Vazquez
Author-email: andres@agavesoft.com.mx
Classifier: Programming Language :: Python :: 3
Classifier: License :: OSI Approved :: MIT License
Classifier: Operating System :: OS Independent
Requires-Python: >=3.6
License-File: LICENSE
